LICENSE
MANIFEST.in
README.md
package.json
setup.py
dash_iframe_message/DashIframeMessage.py
dash_iframe_message/__init__.py
dash_iframe_message/_imports_.py
dash_iframe_message/dash_iframe_message.min.js
dash_iframe_message/dash_iframe_message.min.js.map
dash_iframe_message/metadata.json
dash_iframe_message/package-info.json
dash_iframe_message.egg-info/PKG-INFO
dash_iframe_message.egg-info/SOURCES.txt
dash_iframe_message.egg-info/dependency_links.txt
dash_iframe_message.egg-info/top_level.txt
tests/test_usage.py