Metadata-Version: 2.1
Name: dash-iframe-message
Version: 0.0.1
Summary: Project Description
Author: mapix <mapix.me@gmail.com>
License: MIT
Classifier: Framework :: Dash
License-File: LICENSE
